{
  "version": "5",
  "dialect": "mysql",
  "id": "1654f3da-21a3-4a7b-a036-abe77120d1c2",
  "prevId": "680ea36e-d2c6-4462-ac56-b30cc3720083",
  "tables": {
    "category": {
      "name": "category",
      "columns": {
        "id": {
          "name": "id",
          "type": "int",
          "primaryKey": false,
          "notNull": true,
          "autoincrement": true
        },
        "name": {
          "name": "name",
          "type": "varchar(255)",
          "primaryKey": false,
          "notNull": true,
          "autoincrement": false
        },
        "region_id": {
          "name": "region_id",
          "type": "varchar(255)",
          "primaryKey": false,
          "notNull": false,
          "autoincrement": false
        },
        "merchant_id": {
          "name": "merchant_id",
          "type": "varchar(255)",
          "primaryKey": false,
          "notNull": true,
          "autoincrement": false
        }
      },
      "indexes": {
        "idx_name": {
          "name": "idx_name",
          "columns": [
            "name"
          ],
          "isUnique": false
        }
      },
      "foreignKeys": {
        "category_region_id_region_id_fk": {
          "name": "category_region_id_region_id_fk",
          "tableFrom": "category",
          "tableTo": "region",
          "columnsFrom": [
            "region_id"
          ],
          "columnsTo": [
            "id"
          ],
          "onDelete": "set null",
          "onUpdate": "cascade"
        },
        "category_merchant_id_merchant_id_fk": {
          "name": "category_merchant_id_merchant_id_fk",
          "tableFrom": "category",
          "tableTo": "merchant",
          "columnsFrom": [
            "merchant_id"
          ],
          "columnsTo": [
            "id"
          ],
          "onDelete": "cascade",
          "onUpdate": "cascade"
        }
      },
      "compositePrimaryKeys": {
        "category_id": {
          "name": "category_id",
          "columns": [
            "id"
          ]
        }
      },
      "uniqueConstraints": {},
      "checkConstraint": {}
    },
    "merchant": {
      "name": "merchant",
      "columns": {
        "id": {
          "name": "id",
          "type": "varchar(255)",
          "primaryKey": false,
          "notNull": true,
          "autoincrement": false
        },
        "name": {
          "name": "name",
          "type": "varchar(255)",
          "primaryKey": false,
          "notNull": true,
          "autoincrement": false
        },
        "website": {
          "name": "website",
          "type": "varchar(255)",
          "primaryKey": false,
          "notNull": false,
          "autoincrement": false
        }
      },
      "indexes": {},
      "foreignKeys": {},
      "compositePrimaryKeys": {
        "merchant_id": {
          "name": "merchant_id",
          "columns": [
            "id"
          ]
        }
      },
      "uniqueConstraints": {},
      "checkConstraint": {}
    },
    "model": {
      "name": "model",
      "columns": {
        "id": {
          "name": "id",
          "type": "int",
          "primaryKey": false,
          "notNull": true,
          "autoincrement": true
        },
        "name": {
          "name": "name",
          "type": "varchar(255)",
          "primaryKey": false,
          "notNull": true,
          "autoincrement": false
        },
        "merchant_id": {
          "name": "merchant_id",
          "type": "varchar(255)",
          "primaryKey": false,
          "notNull": true,
          "autoincrement": false
        },
        "category_id": {
          "name": "category_id",
          "type": "int",
          "primaryKey": false,
          "notNull": false,
          "autoincrement": false
        },
        "cpu": {
          "name": "cpu",
          "type": "varchar(255)",
          "primaryKey": false,
          "notNull": false,
          "autoincrement": false
        },
        "gpu": {
          "name": "gpu",
          "type": "varchar(255)",
          "primaryKey": false,
          "notNull": false,
          "autoincrement": false
        },
        "core": {
          "name": "core",
          "type": "int",
          "primaryKey": false,
          "notNull": false,
          "autoincrement": false
        },
        "memory": {
          "name": "memory",
          "type": "int",
          "primaryKey": false,
          "notNull": false,
          "autoincrement": false
        },
        "storage": {
          "name": "storage",
          "type": "int",
          "primaryKey": false,
          "notNull": false,
          "autoincrement": false
        },
        "bandwidth": {
          "name": "bandwidth",
          "type": "int",
          "primaryKey": false,
          "notNull": false,
          "autoincrement": false
        },
        "region_id": {
          "name": "region_id",
          "type": "varchar(255)",
          "primaryKey": false,
          "notNull": false,
          "autoincrement": false
        }
      },
      "indexes": {
        "idx_name": {
          "name": "idx_name",
          "columns": [
            "name"
          ],
          "isUnique": false
        }
      },
      "foreignKeys": {
        "model_merchant_id_merchant_id_fk": {
          "name": "model_merchant_id_merchant_id_fk",
          "tableFrom": "model",
          "tableTo": "merchant",
          "columnsFrom": [
            "merchant_id"
          ],
          "columnsTo": [
            "id"
          ],
          "onDelete": "cascade",
          "onUpdate": "cascade"
        },
        "model_category_id_category_id_fk": {
          "name": "model_category_id_category_id_fk",
          "tableFrom": "model",
          "tableTo": "category",
          "columnsFrom": [
            "category_id"
          ],
          "columnsTo": [
            "id"
          ],
          "onDelete": "set null",
          "onUpdate": "cascade"
        },
        "model_region_id_region_id_fk": {
          "name": "model_region_id_region_id_fk",
          "tableFrom": "model",
          "tableTo": "region",
          "columnsFrom": [
            "region_id"
          ],
          "columnsTo": [
            "id"
          ],
          "onDelete": "set null",
          "onUpdate": "cascade"
        }
      },
      "compositePrimaryKeys": {
        "model_id": {
          "name": "model_id",
          "columns": [
            "id"
          ]
        }
      },
      "uniqueConstraints": {},
      "checkConstraint": {}
    },
    "price": {
      "name": "price",
      "columns": {
        "id": {
          "name": "id",
          "type": "int",
          "primaryKey": false,
          "notNull": true,
          "autoincrement": true
        },
        "cycle": {
          "name": "cycle",
          "type": "varchar(255)",
          "primaryKey": false,
          "notNull": true,
          "autoincrement": false,
          "default": "'monthly'"
        },
        "amount": {
          "name": "amount",
          "type": "double",
          "primaryKey": false,
          "notNull": true,
          "autoincrement": false
        },
        "unit": {
          "name": "unit",
          "type": "varchar(255)",
          "primaryKey": false,
          "notNull": true,
          "autoincrement": false,
          "default": "'USD'"
        },
        "model_id": {
          "name": "model_id",
          "type": "int",
          "primaryKey": false,
          "notNull": true,
          "autoincrement": false
        }
      },
      "indexes": {},
      "foreignKeys": {
        "price_model_id_model_id_fk": {
          "name": "price_model_id_model_id_fk",
          "tableFrom": "price",
          "tableTo": "model",
          "columnsFrom": [
            "model_id"
          ],
          "columnsTo": [
            "id"
          ],
          "onDelete": "cascade",
          "onUpdate": "cascade"
        }
      },
      "compositePrimaryKeys": {
        "price_id": {
          "name": "price_id",
          "columns": [
            "id"
          ]
        }
      },
      "uniqueConstraints": {},
      "checkConstraint": {}
    },
    "region": {
      "name": "region",
      "columns": {
        "id": {
          "name": "id",
          "type": "varchar(255)",
          "primaryKey": false,
          "notNull": true,
          "autoincrement": false
        },
        "name": {
          "name": "name",
          "type": "varchar(255)",
          "primaryKey": false,
          "notNull": true,
          "autoincrement": false
        },
        "country": {
          "name": "country",
          "type": "varchar(255)",
          "primaryKey": false,
          "notNull": false,
          "autoincrement": false
        }
      },
      "indexes": {},
      "foreignKeys": {
        "region_country_region_id_fk": {
          "name": "region_country_region_id_fk",
          "tableFrom": "region",
          "tableTo": "region",
          "columnsFrom": [
            "country"
          ],
          "columnsTo": [
            "id"
          ],
          "onDelete": "set null",
          "onUpdate": "cascade"
        }
      },
      "compositePrimaryKeys": {
        "region_id": {
          "name": "region_id",
          "columns": [
            "id"
          ]
        }
      },
      "uniqueConstraints": {},
      "checkConstraint": {}
    }
  },
  "views": {},
  "_meta": {
    "schemas": {},
    "tables": {},
    "columns": {}
  },
  "internal": {
    "tables": {},
    "indexes": {}
  }
}